memorydelaysmtphandler/__init__.py
memorydelaysmtphandler/memorydelaysmtphandler.py
memorydelaysmtphandler-1.0.2.dist-info/METADATA
memorydelaysmtphandler-1.0.2.dist-info/WHEEL
memorydelaysmtphandler-1.0.2.dist-info/licenses/LICENSE
memorydelaysmtphandler-1.0.2.dist-info/RECORD
