Metadata-Version: 2.3
Name: memorydelaysmtphandler
Version: 1.0.2
Summary: MemoryDelaySmtpHandler will create a bundle of events in a single email and sent it after a delay.
Project-URL: Homepage, https://github.com/void127001/memorydelaysmtphandler
Project-URL: Issues, https://github.com/void127001/memorydelaysmtphandler/issues
Author: void127001
License-File: LICENSE
Classifier: License :: OSI Approved :: GNU Lesser General Public License v2 or later (LGPLv2+)
Classifier: Operating System :: OS Independent
Classifier: Programming Language :: Python :: 3
Requires-Python: >=3.8
